pysnooper/__init__.py
pysnooper/pycompat.py
pysnooper/pysnooper.py
pysnooper/tracer.py
pysnooper/utils.py
pysnooper/third_party/__init__.py
pysnooper/third_party/decorator.py
pysnooper/third_party/six.py
PySnooper_g-0.1.0.dist-info/AUTHORS
PySnooper_g-0.1.0.dist-info/LICENSE
PySnooper_g-0.1.0.dist-info/METADATA
PySnooper_g-0.1.0.dist-info/WHEEL
PySnooper_g-0.1.0.dist-info/top_level.txt
PySnooper_g-0.1.0.dist-info/RECORD
